{
  "login": {
    "legacy": "theme.mp3",
    "new": "Ombre de Bastion.mp3"
  },
  "trial": {
    "legacy": "exterieur.mp3",
    "new": "Gravel Starlight.mp3"
  },
  "zones": {
    "0": {
      "legacy": "exterieur.mp3",
      "new": "Velours Moteur.mp3"
    },
    "1": {
      "legacy": "exterieur.mp3",
      "new": "Velours Moteur(1).mp3"
    },
    "2": {
      "legacy": "exterieur.mp3",
      "new": null
    },
    "3": {
      "legacy": "exterieur.mp3",
      "new": null
    },
    "4": {
      "legacy": "exterieur.mp3",
      "new": null
    },
    "5": {
      "legacy": "exterieur.mp3",
      "new": null
    },
    "6": {
      "legacy": "exterieur.mp3",
      "new": null
    },
    "7": {
      "legacy": "exterieur.mp3",
      "new": null
    }
  }
}